mcp_devdiag/__init__.py
mcp_devdiag/analyzer.py
mcp_devdiag/config.py
mcp_devdiag/export_s3.py
mcp_devdiag/incident.py
mcp_devdiag/limits.py
mcp_devdiag/schema.py
mcp_devdiag/security.py
mcp_devdiag/security_jwks.py
mcp_devdiag/server.py
mcp_devdiag/tail.py
mcp_devdiag/tools_devdiag.py
mcp_devdiag/tools_diag.py
mcp_devdiag/probes/__init__.py
mcp_devdiag/probes/adapters.py
mcp_devdiag/probes/adapters_playwright.py
mcp_devdiag/probes/bundle.py
mcp_devdiag/probes/csp_headers.py
mcp_devdiag/probes/csp_inline.py
mcp_devdiag/probes/dom_overlays.py
mcp_devdiag/probes/fixes.py
mcp_devdiag/probes/framework_versions.py
mcp_devdiag/probes/handshake.py
mcp_devdiag/probes/score.py
mcp_devdiag/probes/types.py
mcp_devdiag/schemas/probe_result.json
mcp_devdiag-0.2.1.dist-info/licenses/LICENSE
mcp_devdiag-0.2.1.dist-info/METADATA
mcp_devdiag-0.2.1.dist-info/WHEEL
mcp_devdiag-0.2.1.dist-info/entry_points.txt
mcp_devdiag-0.2.1.dist-info/top_level.txt
mcp_devdiag-0.2.1.dist-info/RECORD
