Metadata-Version: 2.4
Name: mcp-devdiag
Version: 0.2.1
Summary: MCP server for autonomous dev diagnostics (logs, CORS, env, network).
Author: Leo Klemet
License: MIT
Project-URL: Homepage, https://github.com/leok974/mcp-devdiag
Project-URL: Documentation, https://github.com/leok974/mcp-devdiag#readme
Project-URL: Changelog, https://github.com/leok974/mcp-devdiag/blob/main/CHANGELOG.md
Project-URL: Issues, https://github.com/leok974/mcp-devdiag/issues
Project-URL: Source, https://github.com/leok974/mcp-devdiag
Keywords: mcp,diagnostics,observability,cors,csp,copilot
Classifier: Development Status :: 5 - Production/Stable
Classifier: Intended Audience :: Developers
Classifier: License :: OSI Approved :: MIT License
Classifier: Programming Language :: Python :: 3
Classifier: Programming Language :: Python :: 3.10
Classifier: Programming Language :: Python :: 3.11
Classifier: Programming Language :: Python :: 3.12
Classifier: Programming Language :: Python :: 3.13
Classifier: Topic :: Internet :: WWW/HTTP
Classifier: Topic :: System :: Monitoring
Classifier: Typing :: Typed
Requires-Python: >=3.10
License-File: LICENSE
Requires-Dist: fastmcp>=0.2.0
Requires-Dist: httpx>=0.27.0
Requires-Dist: pydantic>=2
Requires-Dist: python-jose[cryptography]>=3.3.0
Provides-Extra: dev
Requires-Dist: pytest>=8.0; extra == "dev"
Requires-Dist: pytest-asyncio>=0.23.0; extra == "dev"
Requires-Dist: ruff>=0.1.0; extra == "dev"
Requires-Dist: mypy>=1.7.0; extra == "dev"
Provides-Extra: playwright
Requires-Dist: playwright>=1.40.0; extra == "playwright"
Provides-Extra: export
Requires-Dist: boto3>=1.34.0; extra == "export"
Dynamic: license-file
